sensible/__init__.py
sensible/loginit.py
sensible-1.0.3.dist-info/DESCRIPTION.rst
sensible-1.0.3.dist-info/METADATA
sensible-1.0.3.dist-info/RECORD
sensible-1.0.3.dist-info/WHEEL
sensible-1.0.3.dist-info/metadata.json
sensible-1.0.3.dist-info/top_level.txt
