Metadata-Version: 2.0
Name: sensible
Version: 1.0.3
Summary: A simple and sensible logging config
Home-page: http://github.com/nogibjj/sensible
Author: Noah Gift
Author-email: noah.gift@gmail.com
License: UNKNOWN
Platform: UNKNOWN
Classifier: License :: OSI Approved :: MIT License
Classifier: Programming Language :: Python
